pyscfg/__init__.py
pyscfg/core.py
pyscfg/helpers.py
pyscfg/stores.py
pyscfg-0.2.1.dist-info/LICENSE
pyscfg-0.2.1.dist-info/METADATA
pyscfg-0.2.1.dist-info/WHEEL
pyscfg-0.2.1.dist-info/top_level.txt
pyscfg-0.2.1.dist-info/RECORD
