Metadata-Version: 2.1
Name: pyscfg
Version: 0.2.1
Summary: simple handling of user configuration
Home-page: UNKNOWN
Author: Christopher Mertens
Author-email: suppetia@gmx.de
License: UNKNOWN
Project-URL: Github, https://github.com/suppetia/pyscfg
Platform: UNKNOWN
Classifier: Development Status :: 4 - Beta
Classifier: Intended Audience :: Developers
Classifier: License :: OSI Approved :: BSD License
Classifier: Programming Language :: Python :: 3.6
Classifier: Programming Language :: Python :: 3.7
Classifier: Programming Language :: Python :: 3.8
Classifier: Programming Language :: Python :: 3.9
Classifier: Programming Language :: Python :: 3.10
Requires-Python: >=3.6.0
Requires-Dist: PyYAML (>=5.3.1)
